pluralize/__init__.py
pluralize-20250901.1.dist-info/METADATA
pluralize-20250901.1.dist-info/WHEEL
pluralize-20250901.1.dist-info/top_level.txt
pluralize-20250901.1.dist-info/RECORD
