Metadata-Version: 2.4
Name: pluralize
Version: 20250901.1
Summary: i18n + pluralization library with multi-plural form support and thread safe for web apps
Author-email: Massimo Di Pierro <massimo.dipierro@gmail.com>
Project-URL: Homepage, https://github.com/web2py/pluralize
Project-URL: Bug Tracker, https://github.com/web2py/yatl/pluralize
Classifier: Programming Language :: Python :: 3
Classifier: License :: OSI Approved :: BSD License
Classifier: Operating System :: OS Independent
Requires-Python: >=3.7
Provides-Extra: manage
Requires-Dist: twine; extra == "manage"
